{"type": "FeatureCollection", "features": [{"type": "Feature", "geometry": {"type": "Point", "coordinates": [-73.579006, 45.507418]}, "properties": {"name": "Trottier"}}, {"type": "Feature", "geometry": {"type": "Point", "coordinates": [-73.57643, 45.50614]}, "properties": {"name": "McConnell"}}, {"type": "Feature", "geometry": {"type": "Point", "coordinates": [-73.57764, 45.50523]}, "properties": {"name": "Arts"}}, {"type": "Feature", "geometry": {"type": "Point", "coordinates": [-73.57589, 45.50326]}, "properties": {"name": "Mclennan_Library"}}, {"type": "Feature", "geometry": {"type": "Point", "coordinates": [-73.57643, 45.50249]}, "properties": {"name": "Bronfman"}}, {"type": "Feature", "geometry": {"type": "Point", "coordinates": [-73.57817, 45.50353]}, "properties": {"name": "SSMU"}}, {"type": "Feature", "geometry": {"type": "Point", "coordinates": [-73.57886999845503, 45.50759881612314]}, "properties": {"name": "p1"}}, {"type": "Feature", "geometry": {"type": "Point", "coordinates": [-73.57645332813262, 45.50640517402293]}, "properties": {"name": "p2"}}, {"type": "Feature", "geometry": {"type": "Point", "coordinates": [-73.57660353183746, 45.50624539323829]}, "properties": {"name": "p3"}}, {"type": "Feature", "geometry": {"type": "Point", "coordinates": [-73.57914626598358, 45.507164596492906]}, "properties": {"name": "p4"}}, {"type": "Feature", "geometry": {"type": "Point", "coordinates": [-73.57715338468552, 45.50615140432961]}, "properties": {"name": "p5"}}, {"type": "Feature", "geometry": {"type": "Point", "coordinates": [-73.57681810855865, 45.50600290153401]}, "properties": {"name": "p6"}}, {"type": "Feature", "geometry": {"type": "Point", "coordinates": [-73.5774591565132, 45.50582432170404]}, "properties": {"name": "p7"}}, {"type": "Feature", "geometry": {"type": "Point", "coordinates": [-73.57709705829619, 45.50556115039571]}, "properties": {"name": "p8"}}, {"type": "Feature", "geometry": {"type": "Point", "coordinates": [-73.5774564743042, 45.50517954981326]}, "properties": {"name": "p9"}}, {"type": "Feature", "geometry": {"type": "Point", "coordinates": [-73.57799023389816, 45.50454792937198]}, "properties": {"name": "p10"}}, {"type": "Feature", "geometry": {"type": "Point", "coordinates": [-73.57730627059937, 45.50421143820787]}, "properties": {"name": "p11"}}, {"type": "Feature", "geometry": {"type": "Point", "coordinates": [-73.5764479637146, 45.504677637719396]}, "properties": {"name": "p12"}}, {"type": "Feature", "geometry": {"type": "Point", "coordinates": [-73.57708096504211, 45.50448965450992]}, "properties": {"name": "p13"}}, {"type": "Feature", "geometry": {"type": "Point", "coordinates": [-73.5747018456459, 45.5037640334334]}, "properties": {"name": "p14"}}, {"type": "Feature", "geometry": {"type": "Point", "coordinates": [-73.57614487409592, 45.50230712349802]}, "properties": {"name": "p15"}}, {"type": "Feature", "geometry": {"type": "Point", "coordinates": [-73.57732504606247, 45.50407608923945]}, "properties": {"name": "p16"}}, {"type": "Feature", "geometry": {"type": "Point", "coordinates": [-73.57615560293198, 45.503532810244565]}, "properties": {"name": "p17"}}, {"type": "Feature", "geometry": {"type": "Point", "coordinates": [-73.57658475637436, 45.50308352019468]}, "properties": {"name": "p18"}}, {"type": "Feature", "geometry": {"type": "Point", "coordinates": [-73.57577741146088, 45.50266994459447]}, "properties": {"name": "p19"}}, {"type": "Feature", "geometry": {"type": "Point", "coordinates": [-73.57794731855392, 45.503758393854724]}, "properties": {"name": "p20"}}]}